tinyqabenchmarkpp/__init__.py
tinyqabenchmarkpp/generate.py
tinyqabenchmarkpp-1.2.3.dist-info/licenses/LICENSE
tinyqabenchmarkpp-1.2.3.dist-info/METADATA
tinyqabenchmarkpp-1.2.3.dist-info/WHEEL
tinyqabenchmarkpp-1.2.3.dist-info/entry_points.txt
tinyqabenchmarkpp-1.2.3.dist-info/top_level.txt
tinyqabenchmarkpp-1.2.3.dist-info/RECORD
