Metadata-Version: 2.4
Name: tinyqabenchmarkpp
Version: 1.2.3
Summary: A tiny synthetic QA LLM benchmark dataset generator using LiteLLM.
Author-email: Vincent Koc <vincentkoc@ieee.org>
Project-URL: Homepage, https://github.com/vincentkoc/tinyqa-benchmark-pp
Project-URL: Bug Tracker, https://github.com/vincentkoc/tinyqa-benchmark-pp/issues
Classifier: Programming Language :: Python :: 3
Classifier: License :: OSI Approved :: Apache Software License
Classifier: Operating System :: OS Independent
Classifier: Topic :: Scientific/Engineering :: Artificial Intelligence
Classifier: Topic :: Text Processing
Classifier: Intended Audience :: Developers
Classifier: Intended Audience :: Science/Research
Requires-Python: >=3.8
License-File: LICENSE
Requires-Dist: litellm>=1.38.3
Requires-Dist: opik
Dynamic: license-file
